{
    "name": "IR3_Assets_all_mods",
    "version": "0.0.1",
    "title": "IR3 Assets: all mods",
    "author": "0n0w1c",
    "description": "Mod pack of all IR3 Assets mods.",
    "factorio_version": "2.0",
    "dependencies": [
        "base >= 2.0.0",
        "IR3_Assets_some_assembly_required",
        "IR3_Assets_alloy_smelting",
        "IR3_Assets_assembling_machines",
        "IR3_Assets_bronze",
        "IR3_Assets_crushing_industry",
        "IR3_Assets_furnaces",
        "IR3_Assets_labs",
        "IR3_Assets_mining_drills",
        "IR3_Assets_pipes",
        "IR3_Assets_power",
        "IR3_Assets_resources",
        "IR3_Assets_robotower",
        "IR3_Assets_steamworks",
        "IR3_Assets_tarmac",
        "IR3_Assets_turrets",
        "IR3_Assets_walls",
        "IR3_Assets_wood_industry"
    ]
}
